[{"iob":0.885,"activity":0.0079,"bolussnooze":0.387,"basaliob":0.235,"netbasalinsulin":0.05,"hightempinsulin":0.4,"time":"2017-02-19T19:05:57.000Z"},{"iob":0.844,"activity":0.0081,"bolussnooze":0.331,"basaliob":0.236,"netbasalinsulin":0.05,"hightempinsulin":0.4,"time":"2017-02-19T19:10:57.000Z"},{"iob":0.802,"activity":0.0084,"bolussnooze":0.272,"basaliob":0.235,"netbasalinsulin":0,"hightempinsulin":0.35,"time":"2017-02-19T19:15:57.000Z"},{"iob":0.759,"activity":0.0087,"bolussnooze":0.218,"basaliob":0.232,"netbasalinsulin":0,"hightempinsulin":0.35,"time":"2017-02-19T19:20:57.000Z"},{"iob":0.714,"activity":0.0089,"bolussnooze":0.171,"basaliob":0.227,"netbasalinsulin":0,"hightempinsulin":0.35,"time":"2017-02-19T19:25:57.000Z"},{"iob":0.668,"activity":0.0092,"bolussnooze":0.129,"basaliob":0.219,"netbasalinsulin":0,"hightempinsulin":0.35,"time":"2017-02-19T19:30:57.000Z"},{"iob":0.622,"activity":0.0094,"bolussnooze":0.093,"basaliob":0.21,"netbasalinsulin":0,"hightempinsulin":0.35,"time":"2017-02-19T19:35:57.000Z"},{"iob":0.574,"activity":0.0095,"bolussnooze":0.063,"basaliob":0.199,"netbasalinsulin":0,"hightempinsulin":0.35,"time":"2017-02-19T19:40:57.000Z"},{"iob":0.526,"activity":0.0096,"bolussnooze":0.039,"basaliob":0.187,"netbasalinsulin":0.05,"hightempinsulin":0.35,"time":"2017-02-19T19:45:57.000Z"},{"iob":0.478,"activity":0.0096,"bolussnooze":0.021,"basaliob":0.174,"netbasalinsulin":0.1,"hightempinsulin":0.35,"time":"2017-02-19T19:50:57.000Z"},{"iob":0.434,"activity":0.0088,"bolussnooze":0.008,"basaliob":0.16,"netbasalinsulin":0.15,"hightempinsulin":0.35,"time":"2017-02-19T19:55:57.000Z"},{"iob":0.393,"activity":0.0083,"bolussnooze":0.001,"basaliob":0.146,"netbasalinsulin":0.2,"hightempinsulin":0.35,"time":"2017-02-19T20:00:57.000Z"},{"iob":0.353,"activity":0.008,"bolussnooze":0,"basaliob":0.132,"netbasalinsulin":0.25,"hightempinsulin":0.35,"time":"2017-02-19T20:05:57.000Z"},{"iob":0.314,"activity":0.0076,"bolussnooze":0,"basaliob":0.119,"netbasalinsulin":0.25,"hightempinsulin":0.35,"time":"2017-02-19T20:10:57.000Z"},{"iob":0.278,"activity":0.0072,"bolussnooze":0,"basaliob":0.106,"netbasalinsulin":0.25,"hightempinsulin":0.35,"time":"2017-02-19T20:15:57.000Z"},{"iob":0.245,"activity":0.0068,"bolussnooze":0,"basaliob":0.094,"netbasalinsulin":0.25,"hightempinsulin":0.35,"time":"2017-02-19T20:20:57.000Z"},{"iob":0.213,"activity":0.0064,"bolussnooze":0,"basaliob":0.082,"netbasalinsulin":0.25,"hightempinsulin":0.35,"time":"2017-02-19T20:25:57.000Z"},{"iob":0.183,"activity":0.0059,"bolussnooze":0,"basaliob":0.071,"netbasalinsulin":0.25,"hightempinsulin":0.35,"time":"2017-02-19T20:30:57.000Z"},{"iob":0.156,"activity":0.0055,"bolussnooze":0,"basaliob":0.061,"netbasalinsulin":0.25,"hightempinsulin":0.35,"time":"2017-02-19T20:35:57.000Z"},{"iob":0.13,"activity":0.0051,"bolussnooze":0,"basaliob":0.051,"netbasalinsulin":0.25,"hightempinsulin":0.35,"time":"2017-02-19T20:40:57.000Z"},{"iob":0.107,"activity":0.0046,"bolussnooze":0,"basaliob":0.043,"netbasalinsulin":0.3,"hightempinsulin":0.35,"time":"2017-02-19T20:45:57.000Z"},{"iob":0.086,"activity":0.0042,"bolussnooze":0,"basaliob":0.035,"netbasalinsulin":0.3,"hightempinsulin":0.35,"time":"2017-02-19T20:50:57.000Z"},{"iob":0.067,"activity":0.0037,"bolussnooze":0,"basaliob":0.028,"netbasalinsulin":0.35,"hightempinsulin":0.35,"time":"2017-02-19T20:55:57.000Z"},{"iob":0.051,"activity":0.0033,"bolussnooze":0,"basaliob":0.021,"netbasalinsulin":0.35,"hightempinsulin":0.35,"time":"2017-02-19T21:00:57.000Z"},{"iob":0.037,"activity":0.0028,"bolussnooze":0,"basaliob":0.016,"netbasalinsulin":0.35,"hightempinsulin":0.35,"time":"2017-02-19T21:05:57.000Z"},{"iob":0.026,"activity":0.0023,"bolussnooze":0,"basaliob":0.012,"netbasalinsulin":0.35,"hightempinsulin":0.35,"time":"2017-02-19T21:10:57.000Z"},{"iob":0.017,"activity":0.0018,"bolussnooze":0,"basaliob":0.008,"netbasalinsulin":0.3,"hightempinsulin":0.3,"time":"2017-02-19T21:15:57.000Z"},{"iob":0.01,"activity":0.0014,"bolussnooze":0,"basaliob":0.006,"netbasalinsulin":0.25,"hightempinsulin":0.25,"time":"2017-02-19T21:20:57.000Z"},{"iob":0.005,"activity":0.001,"bolussnooze":0,"basaliob":0.003,"netbasalinsulin":0.25,"hightempinsulin":0.25,"time":"2017-02-19T21:25:57.000Z"},{"iob":0.002,"activity":0.0006,"bolussnooze":0,"basaliob":0.002,"netbasalinsulin":0.2,"hightempinsulin":0.2,"time":"2017-02-19T21:30:57.000Z"},{"iob":0.001,"activity":0.0002,"bolussnooze":0,"basaliob":0.001,"netbasalinsulin":0.15,"hightempinsulin":0.15,"time":"2017-02-19T21:35:57.000Z"},{"iob":0,"activity":0.0001,"bolussnooze":0,"basaliob":0,"netbasalinsulin":0.15,"hightempinsulin":0.15,"time":"2017-02-19T21:40:57.000Z"},{"iob":0,"activity":0.0001,"bolussnooze":0,"basaliob":0,"netbasalinsulin":0.1,"hightempinsulin":0.1,"time":"2017-02-19T21:45:57.000Z"},{"iob":0,"activity":0,"bolussnooze":0,"basaliob":0,"netbasalinsulin":0.05,"hightempinsulin":0.05,"time":"2017-02-19T21:50:57.000Z"},{"iob":0,"activity":0,"bolussnooze":0,"basaliob":0,"netbasalinsulin":0,"hightempinsulin":0,"time":"2017-02-19T21:55:57.000Z"},{"iob":0,"activity":0,"bolussnooze":0,"basaliob":0,"netbasalinsulin":0,"hightempinsulin":0,"time":"2017-02-19T22:00:57.000Z"},{"iob":0,"activity":0,"bolussnooze":0,"basaliob":0,"netbasalinsulin":0,"hightempinsulin":0,"time":"2017-02-19T22:05:57.000Z"},{"iob":0,"activity":0,"bolussnooze":0,"basaliob":0,"netbasalinsulin":0,"hightempinsulin":0,"time":"2017-02-19T22:10:57.000Z"},{"iob":0,"activity":0,"bolussnooze":0,"basaliob":0,"netbasalinsulin":0,"hightempinsulin":0,"time":"2017-02-19T22:15:57.000Z"},{"iob":0,"activity":0,"bolussnooze":0,"basaliob":0,"netbasalinsulin":0,"hightempinsulin":0,"time":"2017-02-19T22:20:57.000Z"},{"iob":0,"activity":0,"bolussnooze":0,"basaliob":0,"netbasalinsulin":0,"hightempinsulin":0,"time":"2017-02-19T22:25:57.000Z"},{"iob":0,"activity":0,"bolussnooze":0,"basaliob":0,"netbasalinsulin":0,"hightempinsulin":0,"time":"2017-02-19T22:30:57.000Z"}]
