{
  "bg": 98, 
  "temp": "absolute", 
  "snoozeBG": 204, 
  "predBGs": {
    "COB": [
      98, 
      94, 
      89, 
      83, 
      75, 
      66, 
      56, 
      45, 
      39, 
      39, 
      39, 
      39, 
      39
    ], 
    "aCOB": [
      98, 
      100, 
      100, 
      99, 
      97, 
      93, 
      88, 
      82, 
      75, 
      67, 
      58, 
      48, 
      39, 
      39, 
      39, 
      39, 
      39, 
      39, 
      39, 
      39, 
      39, 
      39, 
      39, 
      39, 
      39, 
      39, 
      39, 
      39, 
      39, 
      39, 
      39, 
      39, 
      39, 
      39, 
      39, 
      39, 
      39, 
      45, 
      52, 
      59, 
      66, 
      73, 
      80
    ], 
    "IOB": [
      98, 
      94, 
      88, 
      81, 
      72, 
      61, 
      49, 
      39, 
      39, 
      39, 
      39, 
      39, 
      39
    ]
  }, 
  "reason": "COB: 78, Dev: 27, BGI: -8.17, ISF: 92, Target: 101; Eventual BG 39 < 101, bolus snooze: eventual BG range 39-204, temp 0.875 ~ req 0.875U/hr", 
  "COB": 78, 
  "eventualBG": 39, 
  "tick": "+1", 
  "IOB": 3.967
}