{
  "bg": 204, 
  "temp": "absolute", 
  "snoozeBG": 105, 
  "predBGs": {
    "IOB": [
      204, 
      203, 
      201, 
      199, 
      196, 
      192, 
      189, 
      184, 
      180, 
      174, 
      169, 
      163, 
      156, 
      150, 
      144, 
      138, 
      132, 
      127, 
      122, 
      117, 
      113, 
      109, 
      105, 
      102, 
      99, 
      97, 
      95, 
      93, 
      91, 
      90, 
      89, 
      88, 
      88, 
      87
    ]
  }, 
  "rate": 1.1, 
  "reason": "COB: 0, Dev: 24, BGI: -5.07, ISF: 82, Target: 80; Eventual BG 105 >= 80, temp 2.35<1.1U/hr", 
  "COB": 0, 
  "eventualBG": 105, 
  "duration": 30, 
  "tick": -1, 
  "IOB": 1.498
}