{
  "bg": 105, 
  "temp": "absolute", 
  "snoozeBG": 90, 
  "predBGs": {
    "COB": [
      105, 
      106, 
      107, 
      108, 
      108, 
      107, 
      105, 
      104, 
      102, 
      100, 
      98, 
      96, 
      93, 
      91, 
      89, 
      86, 
      84, 
      81, 
      79, 
      76, 
      74, 
      72, 
      70, 
      68, 
      67, 
      66, 
      65, 
      64, 
      64, 
      63, 
      63, 
      63, 
      62, 
      62, 
      61, 
      61, 
      60
    ], 
    "aCOB": [
      105, 
      112, 
      118, 
      122, 
      126, 
      128, 
      129, 
      129, 
      129, 
      127, 
      125, 
      123, 
      120, 
      116, 
      111, 
      106, 
      101, 
      97, 
      92, 
      88, 
      84, 
      80, 
      77, 
      74, 
      71, 
      69, 
      67, 
      65, 
      64, 
      63, 
      62, 
      61, 
      60, 
      59, 
      58, 
      58, 
      57
    ], 
    "IOB": [
      105, 
      106, 
      107, 
      106, 
      105, 
      103, 
      101, 
      97, 
      94, 
      90, 
      86, 
      81, 
      76, 
      71, 
      66, 
      62, 
      57, 
      52, 
      48, 
      43, 
      39
    ]
  }, 
  "rate": 0.6, 
  "reason": "COB: 10, Dev: 9, BGI: -2.43, ISF: 90, Target: 80; Eventual BG 60 < 80, bolus snooze: eventual BG range 60-90; setting current basal of 0.6 as temp. Setting neutral temp basal of 0.6U/hr", 
  "COB": 10, 
  "eventualBG": 60, 
  "duration": 30, 
  "tick": -1, 
  "IOB": 0.801
}