[
  {
    "raw_rate": {
      "_type": "TempBasal", 
      "temp": "absolute", 
      "_description": "TempBasal 2017-02-20T22:43:12 head[2], body[1] op[0x33]", 
      "timestamp": "2017-02-20T22:43:12-08:00", 
      "_body": "00", 
      "_head": "3301", 
      "rate": 0.025, 
      "_date": "0cab165411"
    }, 
    "raw_duration": {
      "_type": "TempBasalDuration", 
      "_description": "TempBasalDuration 2017-02-20T22:43:12 head[2], body[0] op[0x16]", 
      "timestamp": "2017-02-20T22:43:12-08:00", 
      "_body": "", 
      "_head": "1601", 
      "duration (min)": 30, 
      "_date": "0cab165411"
    }, 
    "created_at": "2017-02-20T22:43:12-08:00", 
    "enteredBy": "openaps://medtronic/723", 
    "rate": 0.025, 
    "eventType": "Temp Basal", 
    "timestamp": "2017-02-20T22:43:12-08:00", 
    "duration": "30", 
    "medtronic": "mm://openaps/mm-format-ns-treatments/Temp Basal", 
    "absolute": "0.025"
  }, 
  {
    "raw_rate": {
      "_type": "TempBasal", 
      "temp": "absolute", 
      "_description": "TempBasal 2017-02-20T22:32:49 head[2], body[1] op[0x33]", 
      "timestamp": "2017-02-20T22:32:49-08:00", 
      "_body": "00", 
      "_head": "3334", 
      "rate": 1.3, 
      "_date": "31a0165411"
    }, 
    "raw_duration": {
      "_type": "TempBasalDuration", 
      "_description": "TempBasalDuration 2017-02-20T22:32:49 head[2], body[0] op[0x16]", 
      "timestamp": "2017-02-20T22:32:49-08:00", 
      "_body": "", 
      "_head": "1601", 
      "duration (min)": 30, 
      "_date": "31a0165411"
    }, 
    "created_at": "2017-02-20T22:32:49-08:00", 
    "enteredBy": "openaps://medtronic/723", 
    "rate": 1.3, 
    "eventType": "Temp Basal", 
    "timestamp": "2017-02-20T22:32:49-08:00", 
    "duration": "30", 
    "medtronic": "mm://openaps/mm-format-ns-treatments/Temp Basal", 
    "absolute": "1.3"
  }, 
  {
    "raw_rate": {
      "_type": "TempBasal", 
      "temp": "absolute", 
      "_description": "TempBasal 2017-02-20T22:14:20 head[2], body[1] op[0x33]", 
      "timestamp": "2017-02-20T22:14:20-08:00", 
      "_body": "00", 
      "_head": "3334", 
      "rate": 1.3, 
      "_date": "148e165411"
    }, 
    "raw_duration": {
      "_type": "TempBasalDuration", 
      "_description": "TempBasalDuration 2017-02-20T22:14:20 head[2], body[0] op[0x16]", 
      "timestamp": "2017-02-20T22:14:20-08:00", 
      "_body": "", 
      "_head": "1601", 
      "duration (min)": 30, 
      "_date": "148e165411"
    }, 
    "created_at": "2017-02-20T22:14:20-08:00", 
    "enteredBy": "openaps://medtronic/723", 
    "rate": 1.3, 
    "eventType": "Temp Basal", 
    "timestamp": "2017-02-20T22:14:20-08:00", 
    "duration": "30", 
    "medtronic": "mm://openaps/mm-format-ns-treatments/Temp Basal", 
    "absolute": "1.3"
  }, 
  {
    "raw_rate": {
      "_type": "TempBasal", 
      "temp": "absolute", 
      "_description": "TempBasal 2017-02-20T22:13:40 head[2], body[1] op[0x33]", 
      "timestamp": "2017-02-20T22:13:40-08:00", 
      "_body": "00", 
      "_head": "3334", 
      "rate": 1.3, 
      "_date": "288d165411"
    }, 
    "raw_duration": {
      "_type": "TempBasalDuration", 
      "_description": "TempBasalDuration 2017-02-20T22:13:40 head[2], body[0] op[0x16]", 
      "timestamp": "2017-02-20T22:13:40-08:00", 
      "_body": "", 
      "_head": "1601", 
      "duration (min)": 30, 
      "_date": "288d165411"
    }, 
    "created_at": "2017-02-20T22:13:40-08:00", 
    "enteredBy": "openaps://medtronic/723", 
    "rate": 1.3, 
    "eventType": "Temp Basal", 
    "timestamp": "2017-02-20T22:13:40-08:00", 
    "duration": "30", 
    "medtronic": "mm://openaps/mm-format-ns-treatments/Temp Basal", 
    "absolute": "1.3"
  }, 
  {
    "raw_rate": {
      "_type": "TempBasal", 
      "temp": "absolute", 
      "_description": "TempBasal 2017-02-20T21:56:35 head[2], body[1] op[0x33]", 
      "timestamp": "2017-02-20T21:56:35-08:00", 
      "_body": "00", 
      "_head": "3334", 
      "rate": 1.3, 
      "_date": "23b8155411"
    }, 
    "raw_duration": {
      "_type": "TempBasalDuration", 
      "_description": "TempBasalDuration 2017-02-20T21:56:35 head[2], body[0] op[0x16]", 
      "timestamp": "2017-02-20T21:56:35-08:00", 
      "_body": "", 
      "_head": "1601", 
      "duration (min)": 30, 
      "_date": "23b8155411"
    }, 
    "created_at": "2017-02-20T21:56:35-08:00", 
    "enteredBy": "openaps://medtronic/723", 
    "rate": 1.3, 
    "eventType": "Temp Basal", 
    "timestamp": "2017-02-20T21:56:35-08:00", 
    "duration": "30", 
    "medtronic": "mm://openaps/mm-format-ns-treatments/Temp Basal", 
    "absolute": "1.3"
  }, 
  {
    "raw_rate": {
      "_type": "TempBasal", 
      "temp": "absolute", 
      "_description": "TempBasal 2017-02-20T21:32:30 head[2], body[1] op[0x33]", 
      "timestamp": "2017-02-20T21:32:30-08:00", 
      "_body": "00", 
      "_head": "336e", 
      "rate": 2.75, 
      "_date": "1ea0155411"
    }, 
    "raw_duration": {
      "_type": "TempBasalDuration", 
      "_description": "TempBasalDuration 2017-02-20T21:32:30 head[2], body[0] op[0x16]", 
      "timestamp": "2017-02-20T21:32:30-08:00", 
      "_body": "", 
      "_head": "1601", 
      "duration (min)": 30, 
      "_date": "1ea0155411"
    }, 
    "created_at": "2017-02-20T21:32:30-08:00", 
    "enteredBy": "openaps://medtronic/723", 
    "rate": 2.75, 
    "eventType": "Temp Basal", 
    "timestamp": "2017-02-20T21:32:30-08:00", 
    "duration": "30", 
    "medtronic": "mm://openaps/mm-format-ns-treatments/Temp Basal", 
    "absolute": "2.75"
  }, 
  {
    "raw_rate": {
      "_type": "TempBasal", 
      "temp": "absolute", 
      "_description": "TempBasal 2017-02-20T21:27:31 head[2], body[1] op[0x33]", 
      "timestamp": "2017-02-20T21:27:31-08:00", 
      "_body": "00", 
      "_head": "3358", 
      "rate": 2.2, 
      "_date": "1f9b155411"
    }, 
    "raw_duration": {
      "_type": "TempBasalDuration", 
      "_description": "TempBasalDuration 2017-02-20T21:27:31 head[2], body[0] op[0x16]", 
      "timestamp": "2017-02-20T21:27:31-08:00", 
      "_body": "", 
      "_head": "1601", 
      "duration (min)": 30, 
      "_date": "1f9b155411"
    }, 
    "created_at": "2017-02-20T21:27:31-08:00", 
    "enteredBy": "openaps://medtronic/723", 
    "rate": 2.2, 
    "eventType": "Temp Basal", 
    "timestamp": "2017-02-20T21:27:31-08:00", 
    "duration": "30", 
    "medtronic": "mm://openaps/mm-format-ns-treatments/Temp Basal", 
    "absolute": "2.2"
  }, 
  {
    "raw_rate": {
      "_type": "TempBasal", 
      "temp": "absolute", 
      "_description": "TempBasal 2017-02-20T21:21:37 head[2], body[1] op[0x33]", 
      "timestamp": "2017-02-20T21:21:37-08:00", 
      "_body": "00", 
      "_head": "333e", 
      "rate": 1.55, 
      "_date": "2595155411"
    }, 
    "raw_duration": {
      "_type": "TempBasalDuration", 
      "_description": "TempBasalDuration 2017-02-20T21:21:37 head[2], body[0] op[0x16]", 
      "timestamp": "2017-02-20T21:21:37-08:00", 
      "_body": "", 
      "_head": "1601", 
      "duration (min)": 30, 
      "_date": "2595155411"
    }, 
    "created_at": "2017-02-20T21:21:37-08:00", 
    "enteredBy": "openaps://medtronic/723", 
    "rate": 1.55, 
    "eventType": "Temp Basal", 
    "timestamp": "2017-02-20T21:21:37-08:00", 
    "duration": "30", 
    "medtronic": "mm://openaps/mm-format-ns-treatments/Temp Basal", 
    "absolute": "1.55"
  }, 
  {
    "raw_rate": {
      "_type": "TempBasal", 
      "temp": "absolute", 
      "_description": "TempBasal 2017-02-20T21:02:46 head[2], body[1] op[0x33]", 
      "timestamp": "2017-02-20T21:02:46-08:00", 
      "_body": "00", 
      "_head": "3334", 
      "rate": 1.3, 
      "_date": "2e82155411"
    }, 
    "raw_duration": {
      "_type": "TempBasalDuration", 
      "_description": "TempBasalDuration 2017-02-20T21:02:46 head[2], body[0] op[0x16]", 
      "timestamp": "2017-02-20T21:02:46-08:00", 
      "_body": "", 
      "_head": "1601", 
      "duration (min)": 30, 
      "_date": "2e82155411"
    }, 
    "created_at": "2017-02-20T21:02:46-08:00", 
    "enteredBy": "openaps://medtronic/723", 
    "rate": 1.3, 
    "eventType": "Temp Basal", 
    "timestamp": "2017-02-20T21:02:46-08:00", 
    "duration": "30", 
    "medtronic": "mm://openaps/mm-format-ns-treatments/Temp Basal", 
    "absolute": "1.3"
  }, 
  {
    "raw_rate": {
      "_type": "TempBasal", 
      "temp": "absolute", 
      "_description": "TempBasal 2017-02-20T20:50:02 head[2], body[1] op[0x33]", 
      "timestamp": "2017-02-20T20:50:02-08:00", 
      "_body": "00", 
      "_head": "3328", 
      "rate": 1, 
      "_date": "02b2145411"
    }, 
    "raw_duration": {
      "_type": "TempBasalDuration", 
      "_description": "TempBasalDuration 2017-02-20T20:50:02 head[2], body[0] op[0x16]", 
      "timestamp": "2017-02-20T20:50:02-08:00", 
      "_body": "", 
      "_head": "1601", 
      "duration (min)": 30, 
      "_date": "02b2145411"
    }, 
    "created_at": "2017-02-20T20:50:02-08:00", 
    "enteredBy": "openaps://medtronic/723", 
    "rate": 1, 
    "eventType": "Temp Basal", 
    "timestamp": "2017-02-20T20:50:02-08:00", 
    "duration": "30", 
    "medtronic": "mm://openaps/mm-format-ns-treatments/Temp Basal", 
    "absolute": "1"
  }, 
  {
    "raw_rate": {
      "_type": "TempBasal", 
      "temp": "absolute", 
      "_description": "TempBasal 2017-02-20T20:30:40 head[2], body[1] op[0x33]", 
      "timestamp": "2017-02-20T20:30:40-08:00", 
      "_body": "00", 
      "_head": "3382", 
      "rate": 3.25, 
      "_date": "289e145411"
    }, 
    "raw_duration": {
      "_type": "TempBasalDuration", 
      "_description": "TempBasalDuration 2017-02-20T20:30:40 head[2], body[0] op[0x16]", 
      "timestamp": "2017-02-20T20:30:40-08:00", 
      "_body": "", 
      "_head": "1601", 
      "duration (min)": 30, 
      "_date": "289e145411"
    }, 
    "created_at": "2017-02-20T20:30:40-08:00", 
    "enteredBy": "openaps://medtronic/723", 
    "rate": 3.25, 
    "eventType": "Temp Basal", 
    "timestamp": "2017-02-20T20:30:40-08:00", 
    "duration": "30", 
    "medtronic": "mm://openaps/mm-format-ns-treatments/Temp Basal", 
    "absolute": "3.25"
  }, 
  {
    "raw_rate": {
      "_type": "TempBasal", 
      "temp": "absolute", 
      "_description": "TempBasal 2017-02-20T20:22:34 head[2], body[1] op[0x33]", 
      "timestamp": "2017-02-20T20:22:34-08:00", 
      "_body": "00", 
      "_head": "333c", 
      "rate": 1.5, 
      "_date": "2296145411"
    }, 
    "raw_duration": {
      "_type": "TempBasalDuration", 
      "_description": "TempBasalDuration 2017-02-20T20:22:34 head[2], body[0] op[0x16]", 
      "timestamp": "2017-02-20T20:22:34-08:00", 
      "_body": "", 
      "_head": "1601", 
      "duration (min)": 30, 
      "_date": "2296145411"
    }, 
    "created_at": "2017-02-20T20:22:34-08:00", 
    "enteredBy": "openaps://medtronic/723", 
    "rate": 1.5, 
    "eventType": "Temp Basal", 
    "timestamp": "2017-02-20T20:22:34-08:00", 
    "duration": "30", 
    "medtronic": "mm://openaps/mm-format-ns-treatments/Temp Basal", 
    "absolute": "1.5"
  }, 
  {
    "raw_rate": {
      "_type": "TempBasal", 
      "temp": "absolute", 
      "_description": "TempBasal 2017-02-20T20:12:38 head[2], body[1] op[0x33]", 
      "timestamp": "2017-02-20T20:12:38-08:00", 
      "_body": "00", 
      "_head": "3328", 
      "rate": 1, 
      "_date": "268c145411"
    }, 
    "raw_duration": {
      "_type": "TempBasalDuration", 
      "_description": "TempBasalDuration 2017-02-20T20:12:38 head[2], body[0] op[0x16]", 
      "timestamp": "2017-02-20T20:12:38-08:00", 
      "_body": "", 
      "_head": "1601", 
      "duration (min)": 30, 
      "_date": "268c145411"
    }, 
    "created_at": "2017-02-20T20:12:38-08:00", 
    "enteredBy": "openaps://medtronic/723", 
    "rate": 1, 
    "eventType": "Temp Basal", 
    "timestamp": "2017-02-20T20:12:38-08:00", 
    "duration": "30", 
    "medtronic": "mm://openaps/mm-format-ns-treatments/Temp Basal", 
    "absolute": "1"
  }, 
  {
    "raw_rate": {
      "_type": "TempBasal", 
      "temp": "absolute", 
      "_description": "TempBasal 2017-02-20T20:03:44 head[2], body[1] op[0x33]", 
      "timestamp": "2017-02-20T20:03:44-08:00", 
      "_body": "00", 
      "_head": "3300", 
      "rate": 0, 
      "_date": "2c83145411"
    }, 
    "raw_duration": {
      "_type": "TempBasalDuration", 
      "_description": "TempBasalDuration 2017-02-20T20:03:44 head[2], body[0] op[0x16]", 
      "timestamp": "2017-02-20T20:03:44-08:00", 
      "_body": "", 
      "_head": "1601", 
      "duration (min)": 30, 
      "_date": "2c83145411"
    }, 
    "created_at": "2017-02-20T20:03:44-08:00", 
    "enteredBy": "openaps://medtronic/723", 
    "rate": 0, 
    "eventType": "Temp Basal", 
    "timestamp": "2017-02-20T20:03:44-08:00", 
    "duration": "30", 
    "medtronic": "mm://openaps/mm-format-ns-treatments/Temp Basal", 
    "absolute": "0"
  }, 
  {
    "raw_rate": {
      "_type": "TempBasal", 
      "temp": "absolute", 
      "_description": "TempBasal 2017-02-20T19:51:40 head[2], body[1] op[0x33]", 
      "timestamp": "2017-02-20T19:51:40-08:00", 
      "_body": "00", 
      "_head": "3300", 
      "rate": 0, 
      "_date": "28b3135411"
    }, 
    "raw_duration": {
      "_type": "TempBasalDuration", 
      "_description": "TempBasalDuration 2017-02-20T19:51:40 head[2], body[0] op[0x16]", 
      "timestamp": "2017-02-20T19:51:40-08:00", 
      "_body": "", 
      "_head": "1601", 
      "duration (min)": 30, 
      "_date": "28b3135411"
    }, 
    "created_at": "2017-02-20T19:51:40-08:00", 
    "enteredBy": "openaps://medtronic/723", 
    "rate": 0, 
    "eventType": "Temp Basal", 
    "timestamp": "2017-02-20T19:51:40-08:00", 
    "duration": "30", 
    "medtronic": "mm://openaps/mm-format-ns-treatments/Temp Basal", 
    "absolute": "0"
  }, 
  {
    "raw_rate": {
      "_type": "TempBasal", 
      "temp": "absolute", 
      "_description": "TempBasal 2017-02-20T19:51:18 head[2], body[1] op[0x33]", 
      "timestamp": "2017-02-20T19:51:18-08:00", 
      "_body": "00", 
      "_head": "3300", 
      "rate": 0, 
      "_date": "12b3135411"
    }, 
    "raw_duration": {
      "_type": "TempBasalDuration", 
      "_description": "TempBasalDuration 2017-02-20T19:51:18 head[2], body[0] op[0x16]", 
      "timestamp": "2017-02-20T19:51:18-08:00", 
      "_body": "", 
      "_head": "1601", 
      "duration (min)": 30, 
      "_date": "12b3135411"
    }, 
    "created_at": "2017-02-20T19:51:18-08:00", 
    "enteredBy": "openaps://medtronic/723", 
    "rate": 0, 
    "eventType": "Temp Basal", 
    "timestamp": "2017-02-20T19:51:18-08:00", 
    "duration": "30", 
    "medtronic": "mm://openaps/mm-format-ns-treatments/Temp Basal", 
    "absolute": "0"
  }, 
  {
    "raw_rate": {
      "_type": "TempBasal", 
      "temp": "absolute", 
      "_description": "TempBasal 2017-02-20T19:36:40 head[2], body[1] op[0x33]", 
      "timestamp": "2017-02-20T19:36:40-08:00", 
      "_body": "00", 
      "_head": "3354", 
      "rate": 2.1, 
      "_date": "28a4135411"
    }, 
    "raw_duration": {
      "_type": "TempBasalDuration", 
      "_description": "TempBasalDuration 2017-02-20T19:36:40 head[2], body[0] op[0x16]", 
      "timestamp": "2017-02-20T19:36:40-08:00", 
      "_body": "", 
      "_head": "1601", 
      "duration (min)": 30, 
      "_date": "28a4135411"
    }, 
    "created_at": "2017-02-20T19:36:40-08:00", 
    "enteredBy": "openaps://medtronic/723", 
    "rate": 2.1, 
    "eventType": "Temp Basal", 
    "timestamp": "2017-02-20T19:36:40-08:00", 
    "duration": "30", 
    "medtronic": "mm://openaps/mm-format-ns-treatments/Temp Basal", 
    "absolute": "2.1"
  }, 
  {
    "raw_rate": {
      "_type": "TempBasal", 
      "temp": "absolute", 
      "_description": "TempBasal 2017-02-20T19:26:58 head[2], body[1] op[0x33]", 
      "timestamp": "2017-02-20T19:26:58-08:00", 
      "_body": "00", 
      "_head": "3382", 
      "rate": 3.25, 
      "_date": "3a9a135411"
    }, 
    "raw_duration": {
      "_type": "TempBasalDuration", 
      "_description": "TempBasalDuration 2017-02-20T19:26:58 head[2], body[0] op[0x16]", 
      "timestamp": "2017-02-20T19:26:58-08:00", 
      "_body": "", 
      "_head": "1601", 
      "duration (min)": 30, 
      "_date": "3a9a135411"
    }, 
    "created_at": "2017-02-20T19:26:58-08:00", 
    "enteredBy": "openaps://medtronic/723", 
    "rate": 3.25, 
    "eventType": "Temp Basal", 
    "timestamp": "2017-02-20T19:26:58-08:00", 
    "duration": "30", 
    "medtronic": "mm://openaps/mm-format-ns-treatments/Temp Basal", 
    "absolute": "3.25"
  }, 
  {
    "bolus": {
      "programmed": 0.6, 
      "_type": "Bolus", 
      "_description": "Bolus 2017-02-20T19:25:39 head[8], body[0] op[0x01]", 
      "timestamp": "2017-02-20T19:25:39-08:00", 
      "_body": "", 
      "_head": "0100180018005400", 
      "amount": 0.6, 
      "unabsorbed": 2.1, 
      "duration": 0, 
      "type": "normal", 
      "_date": "2799337411"
    }, 
    "timestamp": "2017-02-20T19:25:39-08:00", 
    "created_at": "2017-02-20T19:25:39-08:00", 
    "enteredBy": "openaps://medtronic/723", 
    "insulin": "0.6", 
    "eventType": "Correction Bolus", 
    "duration": "0", 
    "notes": "Normal bolus (solo, no bolus wizard).\nProgrammed bolus 0.6\nDelivered bolus 0.6\nPercent delivered:  100%", 
    "medtronic": "mm://openaps/mm-format-ns-treatments/Correction Bolus"
  }, 
  {
    "raw_rate": {
      "_type": "TempBasal", 
      "temp": "absolute", 
      "_description": "TempBasal 2017-02-20T19:08:17 head[2], body[1] op[0x33]", 
      "timestamp": "2017-02-20T19:08:17-08:00", 
      "_body": "00", 
      "_head": "3374", 
      "rate": 2.9, 
      "_date": "1188135411"
    }, 
    "raw_duration": {
      "_type": "TempBasalDuration", 
      "_description": "TempBasalDuration 2017-02-20T19:08:17 head[2], body[0] op[0x16]", 
      "timestamp": "2017-02-20T19:08:17-08:00", 
      "_body": "", 
      "_head": "1601", 
      "duration (min)": 30, 
      "_date": "1188135411"
    }, 
    "created_at": "2017-02-20T19:08:17-08:00", 
    "enteredBy": "openaps://medtronic/723", 
    "rate": 2.9, 
    "eventType": "Temp Basal", 
    "timestamp": "2017-02-20T19:08:17-08:00", 
    "duration": "30", 
    "medtronic": "mm://openaps/mm-format-ns-treatments/Temp Basal", 
    "absolute": "2.9"
  }, 
  {
    "bolus": {
      "programmed": 0.6, 
      "_type": "Bolus", 
      "_description": "Bolus 2017-02-20T19:06:29 head[8], body[0] op[0x01]", 
      "timestamp": "2017-02-20T19:06:29-08:00", 
      "_body": "", 
      "_head": "0100180018005000", 
      "amount": 0.6, 
      "unabsorbed": 2, 
      "duration": 0, 
      "type": "normal", 
      "_date": "1d86337411"
    }, 
    "timestamp": "2017-02-20T19:06:29-08:00", 
    "created_at": "2017-02-20T19:06:29-08:00", 
    "enteredBy": "openaps://medtronic/723", 
    "insulin": "0.6", 
    "eventType": "Correction Bolus", 
    "duration": "0", 
    "notes": "Normal bolus (solo, no bolus wizard).\nProgrammed bolus 0.6\nDelivered bolus 0.6\nPercent delivered:  100%", 
    "medtronic": "mm://openaps/mm-format-ns-treatments/Correction Bolus"
  }, 
  {
    "raw_rate": {
      "_type": "TempBasal", 
      "temp": "absolute", 
      "_description": "TempBasal 2017-02-20T18:38:59 head[2], body[1] op[0x33]", 
      "timestamp": "2017-02-20T18:38:59-08:00", 
      "_body": "00", 
      "_head": "3356", 
      "rate": 2.15, 
      "_date": "3ba6125411"
    }, 
    "raw_duration": {
      "_type": "TempBasalDuration", 
      "_description": "TempBasalDuration 2017-02-20T18:38:59 head[2], body[0] op[0x16]", 
      "timestamp": "2017-02-20T18:38:59-08:00", 
      "_body": "", 
      "_head": "1601", 
      "duration (min)": 30, 
      "_date": "3ba6125411"
    }, 
    "created_at": "2017-02-20T18:38:59-08:00", 
    "enteredBy": "openaps://medtronic/723", 
    "rate": 2.15, 
    "eventType": "Temp Basal", 
    "timestamp": "2017-02-20T18:38:59-08:00", 
    "duration": "30", 
    "medtronic": "mm://openaps/mm-format-ns-treatments/Temp Basal", 
    "absolute": "2.15"
  }, 
  {
    "raw_rate": {
      "_type": "TempBasal", 
      "temp": "absolute", 
      "_description": "TempBasal 2017-02-20T18:38:38 head[2], body[1] op[0x33]", 
      "timestamp": "2017-02-20T18:38:38-08:00", 
      "_body": "00", 
      "_head": "3355", 
      "rate": 2.125, 
      "_date": "26a6125411"
    }, 
    "raw_duration": {
      "_type": "TempBasalDuration", 
      "_description": "TempBasalDuration 2017-02-20T18:38:38 head[2], body[0] op[0x16]", 
      "timestamp": "2017-02-20T18:38:38-08:00", 
      "_body": "", 
      "_head": "1601", 
      "duration (min)": 30, 
      "_date": "26a6125411"
    }, 
    "created_at": "2017-02-20T18:38:38-08:00", 
    "enteredBy": "openaps://medtronic/723", 
    "rate": 2.125, 
    "eventType": "Temp Basal", 
    "timestamp": "2017-02-20T18:38:38-08:00", 
    "duration": "30", 
    "medtronic": "mm://openaps/mm-format-ns-treatments/Temp Basal", 
    "absolute": "2.125"
  }, 
  {
    "raw_rate": {
      "_type": "TempBasal", 
      "temp": "absolute", 
      "_description": "TempBasal 2017-02-20T18:32:29 head[2], body[1] op[0x33]", 
      "timestamp": "2017-02-20T18:32:29-08:00", 
      "_body": "00", 
      "_head": "3382", 
      "rate": 3.25, 
      "_date": "1da0125411"
    }, 
    "raw_duration": {
      "_type": "TempBasalDuration", 
      "_description": "TempBasalDuration 2017-02-20T18:32:29 head[2], body[0] op[0x16]", 
      "timestamp": "2017-02-20T18:32:29-08:00", 
      "_body": "", 
      "_head": "1601", 
      "duration (min)": 30, 
      "_date": "1da0125411"
    }, 
    "created_at": "2017-02-20T18:32:29-08:00", 
    "enteredBy": "openaps://medtronic/723", 
    "rate": 3.25, 
    "eventType": "Temp Basal", 
    "timestamp": "2017-02-20T18:32:29-08:00", 
    "duration": "30", 
    "medtronic": "mm://openaps/mm-format-ns-treatments/Temp Basal", 
    "absolute": "3.25"
  }, 
  {
    "raw_rate": {
      "_type": "TempBasal", 
      "temp": "absolute", 
      "_description": "TempBasal 2017-02-20T18:13:19 head[2], body[1] op[0x33]", 
      "timestamp": "2017-02-20T18:13:19-08:00", 
      "_body": "00", 
      "_head": "331f", 
      "rate": 0.775, 
      "_date": "138d125411"
    }, 
    "raw_duration": {
      "_type": "TempBasalDuration", 
      "_description": "TempBasalDuration 2017-02-20T18:13:19 head[2], body[0] op[0x16]", 
      "timestamp": "2017-02-20T18:13:19-08:00", 
      "_body": "", 
      "_head": "1601", 
      "duration (min)": 30, 
      "_date": "138d125411"
    }, 
    "created_at": "2017-02-20T18:13:19-08:00", 
    "enteredBy": "openaps://medtronic/723", 
    "rate": 0.775, 
    "eventType": "Temp Basal", 
    "timestamp": "2017-02-20T18:13:19-08:00", 
    "duration": "30", 
    "medtronic": "mm://openaps/mm-format-ns-treatments/Temp Basal", 
    "absolute": "0.775"
  }, 
  {
    "raw_rate": {
      "_type": "TempBasal", 
      "temp": "absolute", 
      "_description": "TempBasal 2017-02-20T18:09:28 head[2], body[1] op[0x33]", 
      "timestamp": "2017-02-20T18:09:28-08:00", 
      "_body": "00", 
      "_head": "3311", 
      "rate": 0.425, 
      "_date": "1c89125411"
    }, 
    "raw_duration": {
      "_type": "TempBasalDuration", 
      "_description": "TempBasalDuration 2017-02-20T18:09:28 head[2], body[0] op[0x16]", 
      "timestamp": "2017-02-20T18:09:28-08:00", 
      "_body": "", 
      "_head": "1601", 
      "duration (min)": 30, 
      "_date": "1c89125411"
    }, 
    "created_at": "2017-02-20T18:09:28-08:00", 
    "enteredBy": "openaps://medtronic/723", 
    "rate": 0.425, 
    "eventType": "Temp Basal", 
    "timestamp": "2017-02-20T18:09:28-08:00", 
    "duration": "30", 
    "medtronic": "mm://openaps/mm-format-ns-treatments/Temp Basal", 
    "absolute": "0.425"
  }, 
  {
    "carbs": "100", 
    "ratio": "16", 
    "bolus": {
      "_type": "Bolus", 
      "_description": "Bolus 2017-02-20T18:07:21 head[8], body[0] op[0x01]", 
      "timestamp": "2017-02-20T18:07:21-08:00", 
      "_body": "", 
      "appended": [
        {
          "_type": "UnabsorbedInsulinBolus", 
          "_description": "UnabsorbedInsulinBolus unknown head[14], body[0] op[0x5c]", 
          "_body": "", 
          "_head": "5c0e32a0c00c04d0644ad018d6d0", 
          "data": [
            {
              "amount": 1.25, 
              "age": 160
            }, 
            {
              "amount": 0.3, 
              "age": 260
            }, 
            {
              "amount": 2.5, 
              "age": 330
            }, 
            {
              "amount": 0.6, 
              "age": 470
            }
          ], 
          "_date": ""
        }
      ], 
      "programmed": 2.75, 
      "_head": "01006e006e000600", 
      "amount": 2.75, 
      "unabsorbed": 0.15, 
      "duration": 0, 
      "type": "normal", 
      "_date": "1587321411"
    }, 
    "timestamp": "2017-02-20T18:07:21-08:00", 
    "created_at": "2017-02-20T18:07:21-08:00", 
    "wizard": {
      "_type": "BolusWizard", 
      "bg": 0, 
      "bg_target_low": 100, 
      "_description": "BolusWizard 2017-02-20T18:07:21 head[2], body[15] op[0x5b]", 
      "timestamp": "2017-02-20T18:07:21-08:00", 
      "_body": "645000a05a640000fa00000000fab4", 
      "bg_target_high": 180, 
      "carb_ratio": 16, 
      "food_estimate": 6.25, 
      "unabsorbed_insulin_total": 0, 
      "correction_estimate": 0, 
      "carb_input": 100, 
      "_head": "5b00", 
      "bolus_estimate": 6.25, 
      "sensitivity": 90, 
      "_date": "1587121411"
    }, 
    "enteredBy": "openaps://medtronic/723", 
    "insulin": "2.75", 
    "eventType": "Meal Bolus", 
    "duration": "0", 
    "notes": "Normal bolus with wizard.\nProgrammed bolus 2.75\nDelivered bolus 2.75\nPercent delivered:  100%\nFood estimate 6.25\nCorrection estimate 0\nBolus estimate 6.25\nTarget low 100\nTarget high 180\nHypothetical glucose delta -247.5", 
    "medtronic": "mm://openaps/mm-format-ns-treatments/Meal Bolus"
  }, 
  {
    "raw_rate": {
      "_type": "TempBasal", 
      "temp": "absolute", 
      "_description": "TempBasal 2017-02-20T18:03:23 head[2], body[1] op[0x33]", 
      "timestamp": "2017-02-20T18:03:23-08:00", 
      "_body": "00", 
      "_head": "3321", 
      "rate": 0.825, 
      "_date": "1783125411"
    }, 
    "raw_duration": {
      "_type": "TempBasalDuration", 
      "_description": "TempBasalDuration 2017-02-20T18:03:23 head[2], body[0] op[0x16]", 
      "timestamp": "2017-02-20T18:03:23-08:00", 
      "_body": "", 
      "_head": "1601", 
      "duration (min)": 30, 
      "_date": "1783125411"
    }, 
    "created_at": "2017-02-20T18:03:23-08:00", 
    "enteredBy": "openaps://medtronic/723", 
    "rate": 0.825, 
    "eventType": "Temp Basal", 
    "timestamp": "2017-02-20T18:03:23-08:00", 
    "duration": "30", 
    "medtronic": "mm://openaps/mm-format-ns-treatments/Temp Basal", 
    "absolute": "0.825"
  }, 
  {
    "raw_rate": {
      "_type": "TempBasal", 
      "temp": "absolute", 
      "_description": "TempBasal 2017-02-20T17:43:45 head[2], body[1] op[0x33]", 
      "timestamp": "2017-02-20T17:43:45-08:00", 
      "_body": "00", 
      "_head": "3300", 
      "rate": 0, 
      "_date": "2dab115411"
    }, 
    "raw_duration": {
      "_type": "TempBasalDuration", 
      "_description": "TempBasalDuration 2017-02-20T17:43:45 head[2], body[0] op[0x16]", 
      "timestamp": "2017-02-20T17:43:45-08:00", 
      "_body": "", 
      "_head": "1601", 
      "duration (min)": 30, 
      "_date": "2dab115411"
    }, 
    "created_at": "2017-02-20T17:43:45-08:00", 
    "enteredBy": "openaps://medtronic/723", 
    "rate": 0, 
    "eventType": "Temp Basal", 
    "timestamp": "2017-02-20T17:43:45-08:00", 
    "duration": "30", 
    "medtronic": "mm://openaps/mm-format-ns-treatments/Temp Basal", 
    "absolute": "0"
  }, 
  {
    "raw_rate": {
      "_type": "TempBasal", 
      "temp": "absolute", 
      "_description": "TempBasal 2017-02-20T17:34:08 head[2], body[1] op[0x33]", 
      "timestamp": "2017-02-20T17:34:08-08:00", 
      "_body": "00", 
      "_head": "332a", 
      "rate": 1.05, 
      "_date": "08a2115411"
    }, 
    "raw_duration": {
      "_type": "TempBasalDuration", 
      "_description": "TempBasalDuration 2017-02-20T17:34:08 head[2], body[0] op[0x16]", 
      "timestamp": "2017-02-20T17:34:08-08:00", 
      "_body": "", 
      "_head": "1601", 
      "duration (min)": 30, 
      "_date": "08a2115411"
    }, 
    "created_at": "2017-02-20T17:34:08-08:00", 
    "enteredBy": "openaps://medtronic/723", 
    "rate": 1.05, 
    "eventType": "Temp Basal", 
    "timestamp": "2017-02-20T17:34:08-08:00", 
    "duration": "30", 
    "medtronic": "mm://openaps/mm-format-ns-treatments/Temp Basal", 
    "absolute": "1.05"
  }, 
  {
    "raw_rate": {
      "_type": "TempBasal", 
      "temp": "absolute", 
      "_description": "TempBasal 2017-02-20T17:28:09 head[2], body[1] op[0x33]", 
      "timestamp": "2017-02-20T17:28:09-08:00", 
      "_body": "00", 
      "_head": "331a", 
      "rate": 0.65, 
      "_date": "099c115411"
    }, 
    "raw_duration": {
      "_type": "TempBasalDuration", 
      "_description": "TempBasalDuration 2017-02-20T17:28:09 head[2], body[0] op[0x16]", 
      "timestamp": "2017-02-20T17:28:09-08:00", 
      "_body": "", 
      "_head": "1601", 
      "duration (min)": 30, 
      "_date": "099c115411"
    }, 
    "created_at": "2017-02-20T17:28:09-08:00", 
    "enteredBy": "openaps://medtronic/723", 
    "rate": 0.65, 
    "eventType": "Temp Basal", 
    "timestamp": "2017-02-20T17:28:09-08:00", 
    "duration": "30", 
    "medtronic": "mm://openaps/mm-format-ns-treatments/Temp Basal", 
    "absolute": "0.65"
  }, 
  {
    "raw_rate": {
      "_type": "TempBasal", 
      "temp": "absolute", 
      "_description": "TempBasal 2017-02-20T17:24:58 head[2], body[1] op[0x33]", 
      "timestamp": "2017-02-20T17:24:58-08:00", 
      "_body": "00", 
      "_head": "331a", 
      "rate": 0.65, 
      "_date": "3a98115411"
    }, 
    "raw_duration": {
      "_type": "TempBasalDuration", 
      "_description": "TempBasalDuration 2017-02-20T17:24:58 head[2], body[0] op[0x16]", 
      "timestamp": "2017-02-20T17:24:58-08:00", 
      "_body": "", 
      "_head": "1601", 
      "duration (min)": 30, 
      "_date": "3a98115411"
    }, 
    "created_at": "2017-02-20T17:24:58-08:00", 
    "enteredBy": "openaps://medtronic/723", 
    "rate": 0.65, 
    "eventType": "Temp Basal", 
    "timestamp": "2017-02-20T17:24:58-08:00", 
    "duration": "30", 
    "medtronic": "mm://openaps/mm-format-ns-treatments/Temp Basal", 
    "absolute": "0.65"
  }, 
  {
    "raw_rate": {
      "_type": "TempBasal", 
      "temp": "absolute", 
      "_description": "TempBasal 2017-02-20T17:08:03 head[2], body[1] op[0x33]", 
      "timestamp": "2017-02-20T17:08:03-08:00", 
      "_body": "00", 
      "_head": "3354", 
      "rate": 2.1, 
      "_date": "0388115411"
    }, 
    "raw_duration": {
      "_type": "TempBasalDuration", 
      "_description": "TempBasalDuration 2017-02-20T17:08:03 head[2], body[0] op[0x16]", 
      "timestamp": "2017-02-20T17:08:03-08:00", 
      "_body": "", 
      "_head": "1601", 
      "duration (min)": 30, 
      "_date": "0388115411"
    }, 
    "created_at": "2017-02-20T17:08:03-08:00", 
    "enteredBy": "openaps://medtronic/723", 
    "rate": 2.1, 
    "eventType": "Temp Basal", 
    "timestamp": "2017-02-20T17:08:03-08:00", 
    "duration": "30", 
    "medtronic": "mm://openaps/mm-format-ns-treatments/Temp Basal", 
    "absolute": "2.1"
  }
]