{
  "bg": 244, 
  "temp": "absolute", 
  "snoozeBG": 155, 
  "recieved": true, 
  "predBGs": {
    "IOB": [
      244, 
      244, 
      242, 
      240, 
      237, 
      234, 
      229, 
      224, 
      219, 
      212, 
      205, 
      198, 
      190, 
      182, 
      174, 
      167, 
      160, 
      153, 
      147, 
      142, 
      137, 
      132, 
      128, 
      124, 
      121, 
      118, 
      116, 
      114, 
      112, 
      111, 
      109, 
      108, 
      107, 
      107, 
      106, 
      106, 
      105
    ]
  }, 
  "reason": "COB: 0, Dev: 66, BGI: -10.57, ISF: 85, Target: 80; Eventual BG 155 >= 80, temp 2.45<2.8U/hr", 
  "rate": 2.775, 
  "COB": 0, 
  "eventualBG": 155, 
  "timestamp": "2017-02-13T00:53:56.786295", 
  "duration": 30, 
  "tick": "+1", 
  "IOB": 1.822
}