[
  {
    "trend_arrow": "FLAT", 
    "display_time": "2017-02-12T07:47:50-08:00", 
    "noise": 1, 
    "direction": "Flat", 
    "system_time": "2017-02-12T15:33:04-08:00", 
    "sgv": 122, 
    "dateString": "2017-02-12T07:47:50-08:00", 
    "device": "openaps://indy-e1/cgm", 
    "unfiltered": 133280, 
    "rssi": 443, 
    "date": 1486914470000.0, 
    "filtered": 133792, 
    "type": "sgv", 
    "glucose": 122
  }, 
  {
    "trend_arrow": "FLAT", 
    "display_time": "2017-02-12T07:42:50-08:00", 
    "noise": 1, 
    "direction": "Flat", 
    "system_time": "2017-02-12T15:28:04-08:00", 
    "sgv": 123, 
    "dateString": "2017-02-12T07:42:50-08:00", 
    "device": "openaps://indy-e1/cgm", 
    "unfiltered": 133728, 
    "rssi": 444, 
    "date": 1486914170000.0, 
    "filtered": 134752, 
    "type": "sgv", 
    "glucose": 123
  }, 
  {
    "trend_arrow": "FLAT", 
    "display_time": "2017-02-12T07:37:51-08:00", 
    "noise": 1, 
    "direction": "Flat", 
    "system_time": "2017-02-12T15:23:04-08:00", 
    "sgv": 123, 
    "dateString": "2017-02-12T07:37:51-08:00", 
    "device": "openaps://indy-e1/cgm", 
    "unfiltered": 134144, 
    "rssi": 444, 
    "date": 1486913871000.0, 
    "filtered": 136128, 
    "type": "sgv", 
    "glucose": 123
  }, 
  {
    "trend_arrow": "FLAT", 
    "display_time": "2017-02-12T07:32:50-08:00", 
    "noise": 1, 
    "direction": "Flat", 
    "system_time": "2017-02-12T15:18:03-08:00", 
    "sgv": 124, 
    "dateString": "2017-02-12T07:32:50-08:00", 
    "device": "openaps://indy-e1/cgm", 
    "unfiltered": 135232, 
    "rssi": 174, 
    "date": 1486913570000.0, 
    "filtered": 137600, 
    "type": "sgv", 
    "glucose": 124
  }, 
  {
    "trend_arrow": "FLAT", 
    "display_time": "2017-02-12T07:27:50-08:00", 
    "noise": 1, 
    "direction": "Flat", 
    "system_time": "2017-02-12T15:13:04-08:00", 
    "sgv": 126, 
    "dateString": "2017-02-12T07:27:50-08:00", 
    "device": "openaps://indy-e1/cgm", 
    "unfiltered": 136608, 
    "rssi": 174, 
    "date": 1486913270000.0, 
    "filtered": 138784, 
    "type": "sgv", 
    "glucose": 126
  }, 
  {
    "trend_arrow": "FLAT", 
    "display_time": "2017-02-12T07:22:50-08:00", 
    "noise": 1, 
    "direction": "Flat", 
    "system_time": "2017-02-12T15:08:03-08:00", 
    "sgv": 127, 
    "dateString": "2017-02-12T07:22:50-08:00", 
    "device": "openaps://indy-e1/cgm", 
    "unfiltered": 138048, 
    "rssi": 173, 
    "date": 1486912970000.0, 
    "filtered": 139648, 
    "type": "sgv", 
    "glucose": 127
  }
]