[
  {
    "trend_arrow": "FLAT", 
    "display_time": "2017-02-06T10:53:15-08:00", 
    "noise": 1, 
    "direction": "Flat", 
    "system_time": "2017-02-06T18:38:29-08:00", 
    "sgv": 106, 
    "dateString": "2017-02-06T10:53:15-08:00", 
    "device": "openaps://indy-e1/cgm", 
    "unfiltered": 116176, 
    "rssi": 205, 
    "date": 1486407195000.0, 
    "filtered": 110256, 
    "type": "sgv", 
    "glucose": 106
  }, 
  {
    "trend_arrow": "FLAT", 
    "display_time": "2017-02-06T10:48:15-08:00", 
    "noise": 1, 
    "direction": "Flat", 
    "system_time": "2017-02-06T18:33:29-08:00", 
    "sgv": 103, 
    "dateString": "2017-02-06T10:48:15-08:00", 
    "device": "openaps://indy-e1/cgm", 
    "unfiltered": 113632, 
    "rssi": 177, 
    "date": 1486406895000.0, 
    "filtered": 107664, 
    "type": "sgv", 
    "glucose": 103
  }, 
  {
    "trend_arrow": "FLAT", 
    "display_time": "2017-02-06T10:43:15-08:00", 
    "noise": 1, 
    "direction": "Flat", 
    "system_time": "2017-02-06T18:28:29-08:00", 
    "sgv": 97, 
    "dateString": "2017-02-06T10:43:15-08:00", 
    "device": "openaps://indy-e1/cgm", 
    "unfiltered": 108736, 
    "rssi": 200, 
    "date": 1486406595000.0, 
    "filtered": 106752, 
    "type": "sgv", 
    "glucose": 97
  }, 
  {
    "trend_arrow": "FLAT", 
    "display_time": "2017-02-06T10:38:15-08:00", 
    "noise": 1, 
    "direction": "Flat", 
    "system_time": "2017-02-06T18:23:29-08:00", 
    "sgv": 95, 
    "dateString": "2017-02-06T10:38:15-08:00", 
    "device": "openaps://indy-e1/cgm", 
    "unfiltered": 106448, 
    "rssi": 201, 
    "date": 1486406295000.0, 
    "filtered": 107488, 
    "type": "sgv", 
    "glucose": 95
  }, 
  {
    "trend_arrow": "FLAT", 
    "display_time": "2017-02-06T10:33:16-08:00", 
    "noise": 1, 
    "direction": "Flat", 
    "system_time": "2017-02-06T18:18:29-08:00", 
    "sgv": 96, 
    "dateString": "2017-02-06T10:33:16-08:00", 
    "device": "openaps://indy-e1/cgm", 
    "unfiltered": 107216, 
    "rssi": 446, 
    "date": 1486405996000.0, 
    "filtered": 109344, 
    "type": "sgv", 
    "glucose": 96
  }, 
  {
    "trend_arrow": "FLAT", 
    "display_time": "2017-02-06T10:28:15-08:00", 
    "noise": 1, 
    "direction": "Flat", 
    "system_time": "2017-02-06T18:13:29-08:00", 
    "sgv": 97, 
    "dateString": "2017-02-06T10:28:15-08:00", 
    "device": "openaps://indy-e1/cgm", 
    "unfiltered": 108080, 
    "rssi": 201, 
    "date": 1486405695000.0, 
    "filtered": 111632, 
    "type": "sgv", 
    "glucose": 97
  }
]