[
  {
    "trend_arrow": "FLAT", 
    "display_time": "2017-02-16T10:42:47-08:00", 
    "noise": 1, 
    "direction": "Flat", 
    "system_time": "2017-02-16T18:41:57-08:00", 
    "sgv": 121, 
    "dateString": "2017-02-16T10:42:47-08:00", 
    "device": "openaps://indy-e1/cgm", 
    "unfiltered": 133344, 
    "rssi": 178, 
    "date": 1487270567000.0, 
    "filtered": 128752, 
    "type": "sgv", 
    "glucose": 121
  }, 
  {
    "trend_arrow": "FLAT", 
    "display_time": "2017-02-16T10:37:47-08:00", 
    "noise": 1, 
    "direction": "Flat", 
    "system_time": "2017-02-16T18:36:57-08:00", 
    "sgv": 119, 
    "dateString": "2017-02-16T10:37:47-08:00", 
    "device": "openaps://indy-e1/cgm", 
    "unfiltered": 131232, 
    "rssi": 182, 
    "date": 1487270267000.0, 
    "filtered": 127312, 
    "type": "sgv", 
    "glucose": 119
  }, 
  {
    "trend_arrow": "FLAT", 
    "display_time": "2017-02-16T10:32:48-08:00", 
    "noise": 1, 
    "direction": "Flat", 
    "system_time": "2017-02-16T18:31:57-08:00", 
    "sgv": 115, 
    "dateString": "2017-02-16T10:32:48-08:00", 
    "device": "openaps://indy-e1/cgm", 
    "unfiltered": 127616, 
    "rssi": 183, 
    "date": 1487269968000.0, 
    "filtered": 127136, 
    "type": "sgv", 
    "glucose": 115
  }, 
  {
    "trend_arrow": "FLAT", 
    "display_time": "2017-02-16T10:27:48-08:00", 
    "noise": 1, 
    "direction": "Flat", 
    "system_time": "2017-02-16T18:26:57-08:00", 
    "sgv": 113, 
    "dateString": "2017-02-16T10:27:48-08:00", 
    "device": "openaps://indy-e1/cgm", 
    "unfiltered": 126496, 
    "rssi": 176, 
    "date": 1487269668000.0, 
    "filtered": 127424, 
    "type": "sgv", 
    "glucose": 113
  }, 
  {
    "trend_arrow": "FLAT", 
    "display_time": "2017-02-16T10:22:48-08:00", 
    "noise": 1, 
    "direction": "Flat", 
    "system_time": "2017-02-16T18:21:58-08:00", 
    "sgv": 113, 
    "dateString": "2017-02-16T10:22:48-08:00", 
    "device": "openaps://indy-e1/cgm", 
    "unfiltered": 126512, 
    "rssi": 430, 
    "date": 1487269368000.0, 
    "filtered": 127136, 
    "type": "sgv", 
    "glucose": 113
  }, 
  {
    "trend_arrow": "FLAT", 
    "display_time": "2017-02-16T10:17:48-08:00", 
    "noise": 1, 
    "direction": "Flat", 
    "system_time": "2017-02-16T18:16:57-08:00", 
    "sgv": 115, 
    "dateString": "2017-02-16T10:17:48-08:00", 
    "device": "openaps://indy-e1/cgm", 
    "unfiltered": 127616, 
    "rssi": 170, 
    "date": 1487269068000.0, 
    "filtered": 125792, 
    "type": "sgv", 
    "glucose": 115
  }
]