{
  "device": "openaps://indy-e1", 
  "pump": {
    "battery": {
      "status": "normal", 
      "voltage": 1.38
    }, 
    "status": {
      "status": "normal", 
      "timestamp": "2017-02-19T23:29:43.000Z", 
      "bolusing": false, 
      "suspended": false
    }, 
    "reservoir": 52.35, 
    "clock": "2017-02-19T15:29:55-08:00"
  }, 
  "uploader": {
    "battery": 92, 
    "batteryVoltage": 4104
  }, 
  "openaps": {
    "suggested": {
      "bg": 130, 
      "temp": "absolute", 
      "snoozeBG": 153, 
      "timestamp": "2017-02-19T23:31:30.000Z", 
      "reason": "COB: 35, Dev: 101, BGI: -15.47, ISF: 87, Target: 99; Eventual BG 253 >= 99, temp 0.625<1.85U/hr", 
      "rate": 1.85, 
      "COB": 35, 
      "eventualBG": 253, 
      "duration": 30, 
      "tick": "+6", 
      "IOB": 1.44
    }, 
    "iob": {
      "netbasalinsulin": 1.5, 
      "timestamp": "2017-02-19T23:29:55.000Z", 
      "activity": 0.0354, 
      "basaliob": 0.249, 
      "hightempinsulin": 1.7, 
      "bolussnooze": 0.019, 
      "iob": 1.44
    }, 
    "enacted": {
      "bg": 130, 
      "temp": "absolute", 
      "snoozeBG": 153, 
      "recieved": true, 
      "predBGs": {
        "COB": [
          130, 
          131, 
          132, 
          134, 
          136, 
          138, 
          141, 
          145, 
          149, 
          153, 
          158, 
          163, 
          168, 
          173, 
          179, 
          184, 
          190, 
          196, 
          202, 
          208, 
          215, 
          221, 
          226, 
          232, 
          236, 
          240, 
          244, 
          247, 
          249, 
          251, 
          252, 
          253
        ], 
        "aCOB": [
          130, 
          124, 
          119, 
          115, 
          112, 
          109, 
          108, 
          107, 
          106, 
          107, 
          108, 
          110, 
          112, 
          115, 
          118, 
          122, 
          127, 
          131, 
          137, 
          143, 
          149, 
          155, 
          161, 
          167, 
          173, 
          179, 
          184, 
          189, 
          194, 
          199, 
          203, 
          208, 
          212, 
          216, 
          220, 
          223, 
          227, 
          230, 
          233, 
          236, 
          238, 
          241, 
          243
        ], 
        "IOB": [
          130, 
          130, 
          129, 
          128, 
          127, 
          125, 
          123, 
          120, 
          117, 
          113, 
          109, 
          104, 
          99, 
          94, 
          90, 
          87, 
          84, 
          82, 
          80, 
          80, 
          80, 
          80, 
          80, 
          80, 
          80, 
          80, 
          81
        ]
      }, 
      "rate": 1.85, 
      "reason": "COB: 35, Dev: 101, BGI: -15.47, ISF: 87, Target: 99; Eventual BG 253 >= 99, temp 0.625<1.85U/hr", 
      "COB": 35, 
      "eventualBG": 253, 
      "timestamp": "2017-02-19T23:31:50.000Z", 
      "duration": 30, 
      "tick": "+6", 
      "IOB": 1.44
    }
  }, 
  "mmtune": {
    "scanDetails": [
      [
        "916.540", 
        1, 
        -98
      ], 
      [
        "916.564", 
        5, 
        -81
      ], 
      [
        "916.588", 
        5, 
        -86
      ], 
      [
        "916.612", 
        5, 
        -84
      ], 
      [
        "916.636", 
        5, 
        -88
      ], 
      [
        "916.660", 
        5, 
        -86
      ], 
      [
        "916.684", 
        5, 
        -86
      ], 
      [
        "916.708", 
        5, 
        -95
      ]
    ], 
    "setFreq": 916.564, 
    "timestamp": "2017-02-19T23:29:05.000Z", 
    "usedDefault": false
  }
}