{
  "device": "openaps://indy-e1", 
  "pump": {
    "battery": {
      "status": "normal", 
      "voltage": 1.46
    }, 
    "status": {
      "status": "normal", 
      "timestamp": "2017-02-23T08:12:22.000Z", 
      "bolusing": false, 
      "suspended": false
    }, 
    "reservoir": 134.475, 
    "clock": "2017-02-23T00:12:53-08:00"
  }, 
  "uploader": {
    "battery": 100, 
    "batteryVoltage": 4374
  }, 
  "openaps": {
    "suggested": {
      "bg": 76, 
      "temp": "absolute", 
      "snoozeBG": 111, 
      "timestamp": "2017-02-23T08:14:38.000Z", 
      "predBGs": {
        "COB": [
          76, 
          78, 
          81, 
          84, 
          86, 
          88, 
          91, 
          93, 
          95, 
          97, 
          98, 
          99, 
          101, 
          101, 
          102, 
          102, 
          102, 
          102, 
          102, 
          101, 
          101, 
          101, 
          100, 
          100, 
          100, 
          99, 
          99, 
          99, 
          99, 
          98, 
          98, 
          98, 
          98, 
          98, 
          98, 
          98, 
          98, 
          98, 
          98, 
          99, 
          99, 
          99, 
          100
        ], 
        "aCOB": [
          76, 
          87, 
          99, 
          109, 
          119, 
          128, 
          137, 
          145, 
          152, 
          159, 
          164, 
          170, 
          174, 
          177, 
          180, 
          182, 
          183, 
          183, 
          182, 
          182, 
          181, 
          180, 
          180, 
          179, 
          178, 
          178, 
          177, 
          176, 
          176, 
          175, 
          174, 
          174, 
          173, 
          173, 
          172
        ], 
        "IOB": [
          76, 
          78, 
          81, 
          83, 
          86, 
          88, 
          90, 
          92, 
          94, 
          95, 
          96, 
          97, 
          98, 
          98, 
          99, 
          98, 
          98, 
          97, 
          97, 
          96, 
          95, 
          95, 
          94, 
          93, 
          93, 
          92, 
          91, 
          91, 
          90, 
          89, 
          89, 
          88, 
          88, 
          87, 
          87, 
          86
        ]
      }, 
      "reason": "COB: 13, Dev: 3, BGI: 2.03, ISF: 90, Target: 80; Eventual BG 111 >= 80, temp 1.85 >~ req 1.7U/hr", 
      "COB": 13, 
      "eventualBG": 111, 
      "tick": "+5", 
      "IOB": -0.359
    }, 
    "iob": {
      "netbasalinsulin": -0.25, 
      "timestamp": "2017-02-23T08:12:53.000Z", 
      "activity": -0.0045, 
      "basaliob": -0.359, 
      "hightempinsulin": 1, 
      "bolussnooze": 0, 
      "iob": -0.359
    }, 
    "enacted": {
      "bg": 70, 
      "temp": "absolute", 
      "snoozeBG": 118, 
      "recieved": true, 
      "rate": 1.85, 
      "reason": "COB: 15, Dev: -2, BGI: 1.58, ISF: 90, Target: 80; Eventual BG 118 >= 80, temp 0<1.85U/hr", 
      "COB": 15, 
      "eventualBG": 118, 
      "timestamp": "2017-02-23T08:03:51.000Z", 
      "duration": 30, 
      "tick": "+6", 
      "IOB": -0.556
    }
  }, 
  "mmtune": {
    "scanDetails": [
      [
        "916.492", 
        1, 
        -94
      ], 
      [
        "916.540", 
        1, 
        -98
      ], 
      [
        "916.564", 
        4, 
        -78
      ], 
      [
        "916.588", 
        2, 
        -87
      ], 
      [
        "916.612", 
        5, 
        -70
      ], 
      [
        "916.636", 
        5, 
        -66
      ], 
      [
        "916.660", 
        5, 
        -67
      ], 
      [
        "916.684", 
        3, 
        -81
      ]
    ], 
    "setFreq": 916.636, 
    "timestamp": "2017-02-23T08:12:01.000Z", 
    "usedDefault": false
  }
}