{
  "device": "openaps://indy-e1", 
  "pump": {
    "battery": {
      "status": "normal", 
      "voltage": 1.57
    }, 
    "status": {
      "status": "normal", 
      "timestamp": "2017-02-22T01:33:27.000Z", 
      "bolusing": false, 
      "suspended": false
    }, 
    "reservoir": 66.1, 
    "clock": "2017-02-21T17:33:14-08:00"
  }, 
  "uploader": {
    "battery": 90, 
    "batteryVoltage": 4082
  }, 
  "openaps": {
    "suggested": {
      "bg": 185, 
      "temp": "absolute", 
      "snoozeBG": 120, 
      "timestamp": "2017-02-22T01:35:00.000Z", 
      "reason": "COB: 23, Dev: 68, BGI: -6.26, ISF: 88, Target: 80; Eventual BG 120 >= 80, 21m@2.250 = 0.787 > req 0.45+20%. Setting temp basal of 1.5U/hr", 
      "rate": 1.5, 
      "COB": 23, 
      "eventualBG": 120, 
      "duration": 30, 
      "tick": "+6", 
      "IOB": 1.853
    }, 
    "iob": {
      "netbasalinsulin": 1.55, 
      "timestamp": "2017-02-22T01:33:14.000Z", 
      "activity": 0.0142, 
      "basaliob": 1.575, 
      "hightempinsulin": 1.8, 
      "bolussnooze": 0.061, 
      "iob": 1.853
    }, 
    "enacted": {
      "bg": 185, 
      "temp": "absolute", 
      "snoozeBG": 120, 
      "recieved": true, 
      "predBGs": {
        "COB": [
          185, 
          190, 
          194, 
          198, 
          201, 
          203, 
          205, 
          205, 
          205, 
          203, 
          201, 
          198, 
          195, 
          191, 
          187, 
          183, 
          178, 
          173, 
          168, 
          163, 
          159, 
          154, 
          150, 
          147, 
          143, 
          140, 
          138, 
          135, 
          133, 
          131, 
          129, 
          127, 
          125, 
          124, 
          122, 
          122, 
          121, 
          121, 
          120
        ], 
        "aCOB": [
          185, 
          188, 
          191, 
          194, 
          196, 
          197, 
          198, 
          198, 
          196, 
          194, 
          192, 
          188, 
          185, 
          181, 
          176, 
          171, 
          167, 
          162, 
          157, 
          152, 
          148, 
          144, 
          141, 
          137, 
          135, 
          132, 
          130, 
          129, 
          127, 
          126, 
          125, 
          125, 
          124, 
          123, 
          123, 
          122, 
          122, 
          121
        ], 
        "IOB": [
          185, 
          189, 
          192, 
          194, 
          195, 
          194, 
          192, 
          189, 
          183, 
          177, 
          169, 
          159, 
          149, 
          138, 
          128, 
          117, 
          107, 
          97, 
          87, 
          77, 
          69, 
          61, 
          53, 
          46, 
          40, 
          39
        ]
      }, 
      "rate": 1.5, 
      "reason": "COB: 23, Dev: 68, BGI: -6.26, ISF: 88, Target: 80; Eventual BG 120 >= 80, 21m@2.250 = 0.787 > req 0.45+20%. Setting temp basal of 1.5U/hr", 
      "COB": 23, 
      "eventualBG": 120, 
      "timestamp": "2017-02-22T01:35:41.000Z", 
      "duration": 30, 
      "tick": "+6", 
      "IOB": 1.853
    }
  }, 
  "mmtune": {
    "scanDetails": [
      [
        "916.564", 
        3, 
        -89
      ], 
      [
        "916.588", 
        5, 
        -73
      ], 
      [
        "916.612", 
        5, 
        -66
      ], 
      [
        "916.636", 
        5, 
        -55
      ], 
      [
        "916.660", 
        5, 
        -46
      ], 
      [
        "916.684", 
        3, 
        -69
      ], 
      [
        "916.708", 
        3, 
        -75
      ]
    ], 
    "setFreq": 916.66, 
    "timestamp": "2017-02-22T01:32:23.000Z", 
    "usedDefault": false
  }
}