{
  "device": "openaps://indy-e1", 
  "pump": {
    "battery": {
      "status": "normal", 
      "voltage": 1.36
    }, 
    "status": {
      "status": "normal", 
      "timestamp": "2017-02-09T02:10:34.000Z", 
      "bolusing": false, 
      "suspended": false
    }, 
    "reservoir": 99.575, 
    "clock": "2017-02-08T18:10:59-08:00"
  }, 
  "uploader": {
    "battery": 68, 
    "batteryVoltage": 3864
  }, 
  "openaps": {
    "suggested": {
      "bg": 122, 
      "temp": "absolute", 
      "snoozeBG": 141, 
      "timestamp": "2017-02-09T02:12:26.000Z", 
      "predBGs": {
        "IOB": [
          122, 
          126, 
          129, 
          132, 
          135, 
          137, 
          138, 
          139, 
          140, 
          140, 
          140, 
          140, 
          139, 
          137, 
          136, 
          135, 
          133, 
          131, 
          130, 
          128, 
          126, 
          125, 
          123, 
          122, 
          121, 
          120, 
          118, 
          117, 
          116, 
          116, 
          115, 
          114, 
          113, 
          113, 
          112, 
          112, 
          112, 
          112, 
          111
        ]
      }, 
      "reason": "COB: 0, Dev: 23, BGI: 0.25, ISF: 82, Target: 96; Eventual BG 141 >= 96, temp 1.6<1.9U/hr, but 25m left and 1.6 ~ req 1.9U/hr: no action required", 
      "COB": 0, 
      "eventualBG": 141, 
      "tick": "+8", 
      "IOB": 0.044
    }, 
    "iob": {
      "netbasalinsulin": -0.15, 
      "timestamp": "2017-02-09T02:10:59.000Z", 
      "activity": -0.0006, 
      "basaliob": 0.044, 
      "hightempinsulin": 0.35, 
      "bolussnooze": 0, 
      "iob": 0.044
    }, 
    "enacted": {
      "bg": 114, 
      "temp": "absolute", 
      "snoozeBG": 129, 
      "recieved": true, 
      "rate": 1.6, 
      "reason": "COB: 0, Dev: 14, BGI: 0.29, ISF: 82, Target: 96; Eventual BG 129 >= 96, temp 1.3<1.6U/hr", 
      "COB": 0, 
      "eventualBG": 129, 
      "timestamp": "2017-02-09T02:06:03.000Z", 
      "duration": 30, 
      "tick": "+7", 
      "IOB": -0.01
    }
  }, 
  "mmtune": {
    "scanDetails": [
      [
        "916.612", 
        2, 
        -89
      ], 
      [
        "916.636", 
        4, 
        -77
      ], 
      [
        "916.660", 
        5, 
        -74
      ], 
      [
        "916.684", 
        5, 
        -77
      ]
    ], 
    "setFreq": 916.66, 
    "timestamp": "2017-02-09T02:10:14.000Z", 
    "usedDefault": false
  }
}